{
    "labels": {
        "label": {
            "en": "Settings"
        },
        "controls": {
            "field_label": {
                "value": {
                    "en": "Region",
                    "fr": "Region"
                },
                "label": {
                    "en": "Label"
                },
                "control": "core/text"
            }
        }
    },
    "config": {
        "label": {
            "en": "Settings"
        },
        "controls": {
            "selected": {
                "value": "",
                "control": "project/region"
            },
            "container_class": {
                "value": "ctx-form__item grid__cell gutters",
                "control": "core/hidden"
            }
        }
    }
}
